LICENSE
README.md
setup.cfg
setup.py
hl7_tea/__init__.py
hl7_tea.egg-info/PKG-INFO
hl7_tea.egg-info/SOURCES.txt
hl7_tea.egg-info/dependency_links.txt
hl7_tea.egg-info/not-zip-safe
hl7_tea.egg-info/top_level.txt
hl7_tea/mllp/__init__.py
hl7_tea/mllp/listener.py
hl7_tea/mllp/sender.py